{
  "slug": "ratfolkrogue-tob1-2023",
  "desc": "False",
  "name": "Ratfolk Rogue",
  "size": "Small",
  "type": "Humanoid",
  "subtype": "",
  "group": "null",
  "alignment": "Neutral",
  "armor_class": 15,
  "armor_desc": "studded leather",
  "hit_points": 31,
  "hit_dice": "7d6 + 7",
  "speed": {
    "walk": 10
  },
  "strength": 7,
  "dexterity": 16,
  "constitution": 12,
  "intelligence": 14,
  "wisdom": 10,
  "charisma": 10,
  "strength_save": null,
  "dexterity_save": null,
  "constitution_save": null,
  "intelligence_save": null,
  "wisdom_save": null,
  "charisma_save": null,
  "perception": 12,
  "skills": {
    "Acrobatics": 5,
    "Perception": 2,
    "Stealth": 7
  },
  "damage_vulnerabilities": "False",
  "damage_resistances": "False",
  "damage_immunities": "False",
  "condition_immunities": "False",
  "senses": "darkvision 60 ft., passive Perception 12",
  "languages": "Common, Thieves Cant",
  "challenge_rating": "1",
  "cr": 1,
  "actions": [
    {
      "name": "Dagger",
      "desc": "Melee or Ranged Weapon Attack: +5 to hit, reach 5 ft. or range 20/60 ft., one target. Hit: 5 (1d4 + 3) piercing damage plus 7 (2d6) poison damage."
    },
    {
      "name": "Light Crossbow",
      "desc": "Ranged Weapon Attack: +5 to hit, range 80/320 ft., one target. Hit: 7 (1d8 + 3) piercing damage plus 7 (2d6) poison damage."
    }
  ],
  "bonus_actions": [
    {
      "name": "Cunning Action",
      "desc": "The ratfolk rogue takes the Dash, Disengage, or Hide action."
    }
  ],
  "reactions": [],
  "legendary_desc": null,
  "legendary_actions": [],
  "special_abilities": [
    {
      "name": "Nimbleness",
      "desc": "The ratfolk rogue can move through the space of any Medium or larger hostile creature, and such a space isn't difficult terrain for the ratfolk."
    },
    {
      "name": "Pack Tactics",
      "desc": "The ratfolk rogue has advantage on attack rolls against a creature if at least one of the ratfolk's allies is within 5 feet of the creature and the ally isn't incapacitated."
    }
  ],
  "spell_list": [],
  "page_no": 302,
  "environments": [],
  "img_main": "http://api.open5e.com/",
  "document__slug": "tob-2023",
  "document__title": "Tome of Beasts 2023",
  "document__license_url": "http://open5e.com/legal",
  "document__url": "https://koboldpress.com/kpstore/product/tome-of-beasts-1-2023-edition/",
  "v2_converted_path": "/v2/creatures/tob-2023_ratfolk-rogue/"
}