{
  "slug": "murmuring-worm-a5e",
  "desc": "",
  "name": "Murmuring Worm",
  "size": "Huge",
  "type": "Aberration",
  "subtype": "",
  "group": null,
  "alignment": "",
  "armor_class": 16,
  "armor_desc": "",
  "hit_points": 195,
  "hit_dice": "17d12+85",
  "speed": {
    "walk": 40,
    "burrow": 20,
    "climb": 40,
    "swim": 40
  },
  "strength": 20,
  "dexterity": 12,
  "constitution": 20,
  "intelligence": 8,
  "wisdom": 14,
  "charisma": 18,
  "strength_save": null,
  "dexterity_save": null,
  "constitution_save": null,
  "intelligence_save": null,
  "wisdom_save": null,
  "charisma_save": null,
  "perception": null,
  "skills": {},
  "damage_vulnerabilities": "",
  "damage_resistances": "",
  "damage_immunities": "psychic",
  "condition_immunities": "prone",
  "senses": "darkvision 60 ft., tremorsense 60 ft., passive Perception 12",
  "languages": "",
  "challenge_rating": "12",
  "cr": 12,
  "actions": [
    {
      "name": "Multiattack",
      "desc": "The worm constricts once and attacks once with its bite."
    },
    {
      "name": "Constrict",
      "desc": "Melee Weapon Attack: +9 to hit, reach 5 ft., one creature. Hit: 21 (3d10 + 5) bludgeoning damage. The target is grappled (escape DC 17) and restrained while grappled."
    },
    {
      "name": "Bite",
      "desc": "Melee Weapon Attack: +9 to hit, reach 5 ft., one creature. Hit: 21 (3d10 + 5) piercing damage. If the target is killed by this attack  the worm eats its head."
    }
  ],
  "bonus_actions": [
    {
      "name": "Mental Summons",
      "desc": "One creature with an Intelligence score greater than 3 within 120 feet makes a DC 16 Wisdom saving throw. On a failure, it uses its reaction to move up to its Speed towards the worm by the shortest route possible, avoiding hazards but not opportunity attacks. This is a magical charm effect."
    }
  ],
  "reactions": null,
  "legendary_desc": "",
  "legendary_actions": null,
  "special_abilities": [
    {
      "name": "Amphibious",
      "desc": "The worm can breathe air and water."
    },
    {
      "name": "Locate Mind",
      "desc": "The worm is aware of the location and relative intelligence of all creatures with Intelligence scores greater than 3 within 500 feet."
    },
    {
      "name": "Maddening Murmurs",
      "desc": "The worm babbles constantly. A non-aberrant creature that starts its turn within 30 feet and can hear its murmurs makes a DC 14 Intelligence saving throw. On a failure, the creature takes 10 (3d6) psychic damage and is confused until the start of its next turn."
    }
  ],
  "spell_list": [],
  "page_no": 245,
  "environments": [],
  "img_main": null,
  "document__slug": "menagerie",
  "document__title": "Level Up Advanced 5e Monstrous Menagerie",
  "document__license_url": "http://open5e.com/legal",
  "document__url": "https://www.levelup5e.com",
  "v2_converted_path": "/v2/creatures/mmenag_murmuring-worm/"
}