{
  "slug": "warhorse",
  "desc": "",
  "name": "Warhorse",
  "size": "Large",
  "type": "Beast",
  "subtype": "",
  "group": "Miscellaneous Creatures",
  "alignment": "Unaligned",
  "armor_class": 11,
  "armor_desc": null,
  "hit_points": 19,
  "hit_dice": "3d10+3",
  "speed": {
    "walk": 60
  },
  "strength": 18,
  "dexterity": 12,
  "constitution": 13,
  "intelligence": 2,
  "wisdom": 12,
  "charisma": 7,
  "strength_save": null,
  "dexterity_save": null,
  "constitution_save": null,
  "intelligence_save": null,
  "wisdom_save": null,
  "charisma_save": null,
  "perception": null,
  "skills": {},
  "damage_vulnerabilities": "",
  "damage_resistances": "",
  "damage_immunities": "",
  "condition_immunities": "",
  "senses": "passive Perception 11",
  "languages": "",
  "challenge_rating": "1/2",
  "cr": 0.5,
  "actions": [
    {
      "name": "Hooves",
      "desc": "Melee Weapon Attack: +6 to hit, reach 5 ft., one target. Hit: 11 (2d6 + 4) bludgeoning damage.",
      "attack_bonus": 6,
      "damage_dice": "2d6",
      "damage_bonus": 4
    }
  ],
  "bonus_actions": null,
  "reactions": null,
  "legendary_desc": "",
  "legendary_actions": null,
  "special_abilities": [
    {
      "name": "Trampling Charge",
      "desc": "If the horse moves at least 20 ft. straight toward a creature and then hits it with a hooves attack on the same turn, that target must succeed on a DC 14 Strength saving throw or be knocked prone. If the target is prone, the horse can make another attack with its hooves against it as a bonus action."
    }
  ],
  "spell_list": [],
  "page_no": 392,
  "environments": [
    "Urban",
    "Settlement"
  ],
  "img_main": null,
  "document__slug": "wotc-srd",
  "document__title": "5e Core Rules",
  "document__license_url": "http://open5e.com/legal",
  "document__url": "http://dnd.wizards.com/articles/features/systems-reference-document-srd",
  "v2_converted_path": "/v2/creatures/srd_warhorse/"
}