{
  "slug": "nkosi-tob1-2023",
  "desc": "False",
  "name": "Nkosi",
  "size": "Medium",
  "type": "Humanoid",
  "subtype": "",
  "group": "null",
  "alignment": "Shapechanger)",
  "armor_class": 15,
  "armor_desc": "studded leather in Humanoid form",
  "hit_points": 27,
  "hit_dice": "5d8 + 5",
  "speed": {
    "walk": 50
  },
  "strength": 16,
  "dexterity": 16,
  "constitution": 12,
  "intelligence": 10,
  "wisdom": 10,
  "charisma": 8,
  "strength_save": null,
  "dexterity_save": null,
  "constitution_save": null,
  "intelligence_save": null,
  "wisdom_save": null,
  "charisma_save": null,
  "perception": 10,
  "skills": {
    "Survival": 2
  },
  "damage_vulnerabilities": "False",
  "damage_resistances": "False",
  "damage_immunities": "False",
  "condition_immunities": "False",
  "senses": "darkvision 60 ft., passive Perception 10",
  "languages": "Common (can’t speak in lion form)",
  "challenge_rating": "1/2",
  "cr": 0.5,
  "actions": [
    {
      "name": "Bite",
      "desc": "Melee Weapon Attack: +5 to hit, reach 5 ft., one target. Hit: 6 (1d6 + 3) piercing damage."
    },
    {
      "name": "Mambele (Humanoid Form Only)",
      "desc": "Melee or Ranged Weapon Attack: +5 to hit, reach 5 ft. or range 20/60 ft., one target. Hit: 6 (1d6 + 3) piercing damage."
    }
  ],
  "bonus_actions": [
    {
      "name": "Change Shape",
      "desc": "The nkosi transforms into a Large lion or back into its true form, which is Humanoid. Its statistics, other than its size, speed, and AC, are the same in each form. Any equipment it is wearing or carrying isn't transformed. It reverts to its true form if it dies."
    }
  ],
  "reactions": [],
  "legendary_desc": null,
  "legendary_actions": [],
  "special_abilities": [
    {
      "name": "Keen Smell",
      "desc": "The nkosi has advantage on Wisdom (Perception) checks that rely on smell."
    },
    {
      "name": "Pounce",
      "desc": "If the nkosi moves at least 20 feet straight toward a creature and then hits it with a Mambele attack on the same turn, that target must succeed on a DC 13 Strength saving throw or be knocked prone. If the target is prone, the nkosi can make one Bite attack against it as a bonus action."
    }
  ],
  "spell_list": [],
  "page_no": 286,
  "environments": [],
  "img_main": "http://api.open5e.com/",
  "document__slug": "tob-2023",
  "document__title": "Tome of Beasts 2023",
  "document__license_url": "http://open5e.com/legal",
  "document__url": "https://koboldpress.com/kpstore/product/tome-of-beasts-1-2023-edition/",
  "v2_converted_path": "/v2/creatures/tob-2023_nkosi/"
}