{
  "slug": "axe-beak",
  "desc": "An **axe beak** is a tall flightless bird with strong legs and a heavy, wedge-shaped beak. It has a nasty disposition and tends to attack any unfamiliar creature that wanders too close.",
  "name": "Axe Beak",
  "size": "Large",
  "type": "Beast",
  "subtype": "",
  "group": "Miscellaneous Creatures",
  "alignment": "Unaligned",
  "armor_class": 11,
  "armor_desc": null,
  "hit_points": 19,
  "hit_dice": "3d10+3",
  "speed": {
    "walk": 50
  },
  "strength": 14,
  "dexterity": 12,
  "constitution": 12,
  "intelligence": 2,
  "wisdom": 10,
  "charisma": 5,
  "strength_save": null,
  "dexterity_save": null,
  "constitution_save": null,
  "intelligence_save": null,
  "wisdom_save": null,
  "charisma_save": null,
  "perception": null,
  "skills": {},
  "damage_vulnerabilities": "",
  "damage_resistances": "",
  "damage_immunities": "",
  "condition_immunities": "",
  "senses": "passive Perception 10",
  "languages": "",
  "challenge_rating": "1/4",
  "cr": 0.25,
  "actions": [
    {
      "name": "Beak",
      "desc": "Melee Weapon Attack: +4 to hit, reach 5 ft., one target. Hit: 6 (1d8 + 2) slashing damage.",
      "attack_bonus": 4,
      "damage_dice": "1d8",
      "damage_bonus": 2
    }
  ],
  "bonus_actions": null,
  "reactions": null,
  "legendary_desc": "",
  "legendary_actions": null,
  "special_abilities": null,
  "spell_list": [],
  "page_no": 366,
  "environments": [
    "Hill",
    "Jungle",
    "Swamp",
    "Grassland",
    "Forest"
  ],
  "img_main": null,
  "document__slug": "wotc-srd",
  "document__title": "5e Core Rules",
  "document__license_url": "http://open5e.com/legal",
  "document__url": "http://dnd.wizards.com/articles/features/systems-reference-document-srd",
  "v2_converted_path": "/v2/creatures/srd_axe-beak/"
}