{
  "slug": "bugbear_bf",
  "desc": "",
  "name": "Bugbear",
  "size": "Medium",
  "type": "Humanoid",
  "subtype": "",
  "group": "Goblins",
  "alignment": "",
  "armor_class": 14,
  "armor_desc": "hide armor",
  "hit_points": 40,
  "hit_dice": "",
  "speed": {
    "walk": 30
  },
  "strength": 20,
  "dexterity": 14,
  "constitution": 12,
  "intelligence": 8,
  "wisdom": 10,
  "charisma": 8,
  "strength_save": 5,
  "dexterity_save": 2,
  "constitution_save": 1,
  "intelligence_save": -1,
  "wisdom_save": 0,
  "charisma_save": -1,
  "perception": 10,
  "skills": {},
  "damage_vulnerabilities": "",
  "damage_resistances": "",
  "damage_immunities": "",
  "condition_immunities": "",
  "senses": "darkvision 60 ft.",
  "languages": "Common,Goblin",
  "challenge_rating": "1",
  "cr": 1,
  "actions": [
    {
      "name": "Spiked Club",
      "desc": "_Melee Weapon Attack:_ +5 to hit, reach 5 ft., one target. _Hit:_ 12 (2d8+3) piercing damage. A surprised target takes an extra 4 (1d8) piercing damage and must succeed on a DC 13 CON save or be stunned until the end of its next turn."
    },
    {
      "name": "Javelin",
      "desc": "_Melee or Ranged Weapon Attack:_ +6 to hit, reach 5 ft. or range 30/120 ft., one target. _Hit:_ 11 (2d6+4) piercing damage in melee or 7 (1d6+4) piercing damage at range."
    }
  ],
  "bonus_actions": [],
  "reactions": [],
  "legendary_desc": null,
  "legendary_actions": [],
  "special_abilities": [
    {
      "name": "Brutal",
      "desc": "A melee weapon deals one extra die of its damage when the bugbear hits with it (included in the attack)."
    }
  ],
  "spell_list": [],
  "page_no": null,
  "environments": [],
  "img_main": null,
  "document__slug": "blackflag",
  "document__title": "Black Flag SRD",
  "document__license_url": "https://paizo.com/orclicense",
  "document__url": "https://koboldpress.com/black-flag-reference-document/",
  "v2_converted_path": "/v2/creatures/bfrd_bugbear/"
}